pynamodb_mate/__init__.py
pynamodb_mate/_version.py
pynamodb_mate/api.py
pynamodb_mate/cipher.py
pynamodb_mate/compat.py
pynamodb_mate/helpers.py
pynamodb_mate/models.py
pynamodb_mate/paths.py
pynamodb_mate/type_hint.py
pynamodb_mate/attributes/__init__.py
pynamodb_mate/attributes/api.py
pynamodb_mate/attributes/compressed.py
pynamodb_mate/attributes/encrypted.py
pynamodb_mate/attributes/s3backed.py
pynamodb_mate/docs/__init__.py
pynamodb_mate/patterns/__init__.py
pynamodb_mate/patterns/api.py
pynamodb_mate/patterns/cache/__init__.py
pynamodb_mate/patterns/cache/abstract.py
pynamodb_mate/patterns/cache/api.py
pynamodb_mate/patterns/cache/multi_layer.py
pynamodb_mate/patterns/cache/utils.py
pynamodb_mate/patterns/cache/backend/__init__.py
pynamodb_mate/patterns/cache/backend/dynamodb.py
pynamodb_mate/patterns/cache/backend/in_memory.py
pynamodb_mate/patterns/large_attribute/__init__.py
pynamodb_mate/patterns/large_attribute/api.py
pynamodb_mate/patterns/large_attribute/impl.py
pynamodb_mate/patterns/relationship/__init__.py
pynamodb_mate/patterns/relationship/api.py
pynamodb_mate/patterns/relationship/impl.py
pynamodb_mate/patterns/relationship_v2/__init__.py
pynamodb_mate/patterns/relationship_v2/api.py
pynamodb_mate/patterns/relationship_v2/impl.py
pynamodb_mate/patterns/status_tracker/__init__.py
pynamodb_mate/patterns/status_tracker/api.py
pynamodb_mate/patterns/status_tracker/exc.py
pynamodb_mate/patterns/status_tracker/impl.py
pynamodb_mate/tests/__init__.py
pynamodb_mate/tests/base.py
pynamodb_mate/tests/base_test.py
pynamodb_mate/tests/constants.py
pynamodb_mate/tests/document.py
pynamodb_mate/tests/helper.py
pynamodb_mate/tests/paths.py
pynamodb_mate/tests/youtube.py
pynamodb_mate/tests/youtube_v2.py
pynamodb_mate/vendor/__init__.py
pynamodb_mate/vendor/decorator.py
pynamodb_mate/vendor/iterable.py
pynamodb_mate/vendor/mark.py
pynamodb_mate/vendor/mock_aws.py
pynamodb_mate/vendor/pytest_cov_helper.py
pynamodb_mate-6.0.1.1.dist-info/AUTHORS.rst
pynamodb_mate-6.0.1.1.dist-info/LICENSE.txt
pynamodb_mate-6.0.1.1.dist-info/METADATA
pynamodb_mate-6.0.1.1.dist-info/WHEEL
pynamodb_mate-6.0.1.1.dist-info/top_level.txt
pynamodb_mate-6.0.1.1.dist-info/RECORD
