Metadata-Version: 2.1
Name: pynamodb_mate
Version: 6.0.1.1
Summary: Provide Additional Features for pynamodb.
Home-page: https://github.com/MacHu-GWU/pynamodb_mate-project
Download-URL: https://pypi.python.org/pypi/pynamodb_mate/6.0.1.1#downloads
Author: Sanhe Hu
Author-email: husanhe@gmail.com
Maintainer: Sanhe Hu
Maintainer-email: husanhe@gmail.com
License: MIT
Platform: Windows
Platform: MacOS
Platform: Unix
Classifier: Development Status :: 5 - Production/Stable
Classifier: Intended Audience :: Developers
Classifier: License :: OSI Approved :: MIT License
Classifier: Natural Language :: English
Classifier: Operating System :: Microsoft :: Windows
Classifier: Operating System :: MacOS
Classifier: Operating System :: Unix
Classifier: Programming Language :: Python :: 3 :: Only
Classifier: Programming Language :: Python :: 3.7
Classifier: Programming Language :: Python :: 3.8
Classifier: Programming Language :: Python :: 3.9
Classifier: Programming Language :: Python :: 3.10
Classifier: Programming Language :: Python :: 3.11
Classifier: Programming Language :: Python :: 3.12
Requires-Python: >=3.7
License-File: LICENSE.txt
License-File: AUTHORS.rst
Requires-Dist: pynamodb <7.0.0,>=6.0.1
Requires-Dist: iterproxy <1.0.0,>=0.3.1
Requires-Dist: typing-extensions >=4.11.0 ; python_version < "3.12"
Requires-Dist: cached-property >=1.5.2 ; python_version < "3.8"
Provides-Extra: docs
Requires-Dist: Sphinx ==5.3.0 ; extra == 'docs'
Requires-Dist: sphinx-jinja ==2.0.2 ; extra == 'docs'
Requires-Dist: sphinx-copybutton ==0.5.1 ; extra == 'docs'
Requires-Dist: sphinx-design ==0.5.0 ; extra == 'docs'
Requires-Dist: furo ==2023.03.27 ; extra == 'docs'
Requires-Dist: nbsphinx ==0.8.12 ; extra == 'docs'
Requires-Dist: rstobj ==1.2.1 ; extra == 'docs'
Requires-Dist: pygments ==2.15.1 ; extra == 'docs'
Requires-Dist: ipython ==8.10.0 ; extra == 'docs'
Requires-Dist: ipykernel ==6.28.0 ; extra == 'docs'
Requires-Dist: docfly ==2.0.3 ; extra == 'docs'
Requires-Dist: pycryptodome <4.0.0,>=3.18.0 ; extra == 'docs'
Provides-Extra: encrypt
Requires-Dist: pycryptodome <4.0.0,>=3.18.0 ; extra == 'encrypt'
Provides-Extra: tests
Requires-Dist: pytest ; extra == 'tests'
Requires-Dist: pytest-cov ; extra == 'tests'
Requires-Dist: boto3 ; extra == 'tests'
Requires-Dist: boto-session-manager <2.0.0,>=1.7.2 ; extra == 'tests'
Requires-Dist: s3pathlib <3.0.0,>=2.1.2 ; extra == 'tests'
Requires-Dist: pycryptodome <4.0.0,>=3.18.0 ; extra == 'tests'
Requires-Dist: moto <5.0.0,>=4.1.12 ; extra == 'tests'
Requires-Dist: moto[dynamodb,s3] <5.0.0,>=4.1.12 ; extra == 'tests'
